Workbook

Sheet Summary
A1: UNAI — Cost, Benefit & Efficiency
A2: Companion to the UNAI Architecture document. Figures link from the other tabs.
A4: Headline metric | B4: Value
A5: Layer-complexity reduction (10-agent scale) | B5: ='Complexity & Efficiency'!B22 -> 0.9
A6: Maintenance-hour reduction | B6: ='Complexity & Efficiency'!B26 -> 0.90888383
A7: Agents deployed → used (measured disruption run) | B7: ='Run Metrics'!B5&":"&'Run Metrics'!C5 -> 4:1
A8: Schema re-maps eliminated (context switch) | B8: ='Run Metrics'!E9 -> 1
A9: Year-1 investment | B9: ="$"&TEXT('Cost-Benefit'!C18,"0.0")&"M" -> $2.4M
A10: Annual value — midpoint | B10: ="$"&TEXT(('Cost-Benefit'!C27+'Cost-Benefit'!D27)/2,"0.0")&"M" -> $11.5M
A11: Payback (months, low) | B11: ='Cost-Benefit'!C33 -> 3.4810707
A12: 3-yr NPV midpoint | B12: ="$"&TEXT(('Cost-Benefit'!C35+'Cost-Benefit'!D35)/2,"0")&"M" -> $23M
A14: Verdict: technically feasible today; ~90% complexity reduction at enterprise scale; 4–7 month payback.

Sheet Complexity & Efficiency
A1: Architectural Complexity & Maintenance — Gen 1 vs Gen 2
A2: Source: Superagent Technical Specification §4 (10-agent enterprise estate). Blue = input.
A4: Agent | B4: Domain | C4: Gen-1 layers | D4: Gen-1 maint (hrs/mo) | E4: Gen-2 layers (shared) | F4: Gen-2 maint (hrs/mo)
A5: Demand Forecasting | B5: Supply Chain | C5: 7 | D5: 120 | E5: 0 | F5: 8
A6: Inventory Optimization | B6: Supply Chain | C6: 7 | D6: 95 | E6: 0 | F6: 8
A7: Supplier Risk | B7: Procurement | C7: 7 | D7: 80 | E7: 0 | F7: 8
A8: Logistics Tracking | B8: Logistics | C8: 7 | D8: 110 | E8: 0 | F8: 8
A9: Production Scheduling | B9: Supply Chain | C9: 7 | D9: 90 | E9: 0 | F9: 8
A10: Disruption Response | B10: Supply Chain | C10: 7 | D10: 85 | E10: 0 | F10: 8
A11: Finance NL Query | B11: Finance | C11: 7 | D11: 70 | E11: 0 | F11: 8
A12: Procurement | B12: Procurement | C12: 7 | D12: 75 | E12: 0 | F12: 8
A13: Returns Optimization | B13: Supply Chain | C13: 7 | D13: 65 | E13: 0 | F13: 8
A14: Maintenance Prediction | B14: Maintenance | C14: 7 | D14: 88 | E14: 0 | F14: 8
A15: TOTAL | C15: =SUM(C5:C14) -> 70 | D15: =SUM(D5:D14) -> 878 | E15: =SUM(E5:E14) -> 0 | F15: =SUM(F5:F14) -> 80
A18: Derived efficiency
A19: Gen-2 shared layers (built once) | B19: =7 -> 7
A20: Gen-2 tool packs (lightweight, 1 per agent) | B20: =10 -> 10
A21: Gen-1 layer implementations (10×7) | B21: =C15 -> 70
A22: Layer-implementation reduction (layers only, 70→7) | B22: =1-B19/B21 -> 0.9
A23: Reduction incl. tool packs (70→17, conservative) | B23: =1-(B19+B20)/B21 -> 0.75714286
A24: Gen-1 maintenance (hrs/mo) | B24: =D15 -> 878
A25: Gen-2 maintenance (hrs/mo) | B25: =F15 -> 80
A26: Maintenance reduction | B26: =1-B25/B24 -> 0.90888383

Sheet Cost-Benefit
A1: Cost, Benefit & ROI
A2: Source: Superagent Technical Specification §9. Blue = input. All totals/ROI are formulas.
A4: Item | B4: Detail | C4: Low ($M) | D4: High ($M)
A5: Build — engineering (8 FTE × 16 wk) | C5: 1.28 | D5: 1.28
A6: Build — platform architecture + Mistral setup + prototyping | C6: 0.12 | D6: 0.12
A7: Build — SAP sandbox + BTP licenses | C7: 0.08 | D7: 0.08
A8: Build — security audit + pen test | C8: 0.06 | D8: 0.06
A9: Build — PM + QA | C9: 0.16 | D9: 0.16
A10: Build subtotal | C10: =SUM(C5:C9) -> 1.7 | D10: =SUM(D5:D9) -> 1.7
A11: Run — Mistral inference (Small 80% / Large 20%; API or self-host GPU) | C11: 0.2 | D11: 0.34
A12: Run — Kubernetes compute (orchestrator + agents) | C12: 0.11 | D12: 0.11
A13: Run — PostgreSQL + pgvector | C13: 0.072 | D13: 0.072
A14: Run — Redis + NATS + networking | C14: 0.048 | D14: 0.048
A15: Run — Monitoring + logging + PII redaction | C15: 0.036 | D15: 0.036
A16: Run — maintenance team (2 FTE) | C16: 0.24 | D16: 0.24
A17: Annual run subtotal | C17: =SUM(C11:C16) -> 0.706 | D17: =SUM(D11:D16) -> 0.846
A18: Year-1 investment (build + 1yr run) | C18: =C10+C17 -> 2.406 | D18: =D10+D17 -> 2.546
A20: Annual value created
A21: Value driver | B21: Basis | C21: Low ($M) | D21: High ($M)
A22: Inventory carrying-cost reduction | B22: 15–22% | C22: 3.2 | D22: 4.8
A23: Stockout prevention | B23: revenue protection | C23: 2.1 | D23: 3.5
A24: Planner productivity | B24: 40% gain | C24: 1.4 | D24: 2
A25: Disruption response | B25: revenue protected | C25: 1.5 | D25: 2.2
A26: Fraud / duplicate-invoice prevention | B26: AP controls | C26: 0.8 | D26: 1.5
A27: Annual value total | C27: =SUM(C22:C26) -> 9 | D27: =SUM(D22:D26) -> 14
A29: ROI
A30: Metric | C30: Low | D30: High
A31: Discount rate (input) | C31: 0.12
A32: Net annual benefit (value − run) | C32: =C27-C17 -> 8.294 | D32: =D27-D17 -> 13.154
A33: Payback period (months) | C33: =C18/C32*12 -> 3.4810707 | D33: =D18/D32*12 -> 2.3226395
A34: 3-yr gross benefit | C34: =C32*3 -> 24.882 | D34: =D32*3 -> 39.462
A35: 3-yr NPV (discounted) | C35: =-C18+C32/(1+$C$31)+C32/(1+$C$31)^2+C32/(1+$C$31)^3 -> 17.514789 | D35: =-D18+D32/(1+$C$31)+D32/(1+$C$31)^2+D32/(1+$C$31)^3 -> 29.047689

Sheet Run Metrics
A1: Measured Run — Supplier Disruption Response
A2: Output of the working UNAI Studio app (node run-demo.js --sqlite). Real engine outputs.
A4: Metric | B4: Gen-1 | C4: Gen-2 | D4: Note | E4: Reduction
A5: Agents deployed | B5: 4 | C5: 1 | D5: 4 specialist agents → 1 UNAI | E5: =IF(B5=0,"—",1-C5/B5) -> 0.75
A6: Layer implementations | B6: 28 | C6: 11 | D6: 28 (4×7) → 7 shared + 4 packs | E6: =IF(B6=0,"—",1-C6/B6) -> 0.60714286
A7: System transitions during run | B7: 5 | C7: 5 | D7: transitions unavoidable in both | E7: =IF(B7=0,"—",1-C7/B7) -> 0
A8: Systems of record touched | B8: 4 | C8: 4 | D8: SAP MM, SD, FI, Analytics store | E8: =IF(B8=0,"—",1-C8/B8) -> 0
A9: Schema re-maps (context-switch cost) | B9: 5 | C9: 0 | D9: ontology absorbs all re-maps | E9: =IF(B9=0,"—",1-C9/B9) -> 1
A10: Ontology field translations | B10: 0 | C10: 62 | D10: one central mapper | E10: —
A11: A2A messages | B11: 0 | C11: 4 | D11: pub/sub topics | E11: —
A12: Shared layers exercised | B12: 0 | C12: 7 | D12: all 7 layers fired (see Explainability tab) | E12: —
A13: Autonomous actions executed | B13: 0 | C13: 3 | D13: 1 PO + 2 safety-stock updates | E13: —
A14: Human-approval-gated actions | B14: 0 | C14: 1 | D14: $56K PO > $50K limit (HITL) | E14: —

Sheet Explainability
A1: Explainability & Evidence — every decision traced
A2: Output of the Evidence + Explainability layers. Each decision carries confidence, attribution, uncertainty, a gate, and a rationale.
A4: Decision | B4: Confidence | C4: Uncertainty | D4: Primary driver (share) | E4: Mode | F4: Governance gate
A5: Disruption detected: port strike — APAC lanes | B5: 0.93 | C5: ±7% | D5: supplier risk score (70%) | E5: Autonomous | F5: within policy
A6: Demand re-forecast (+12% pull-forward) | B6: 0.88 | C6: ±12% | D6: open sales orders (57%) | E6: Autonomous | F6: within policy
A7: Inventory rebalanced — 2 SKUs short | B7: 0.92 | C7: ±8% | D7: forecast-vs-onhand gap (69%) | E7: Autonomous | F7: within policy
A8: Raise PO FG-1001 (1,084u, $46,070) — rerouted | B8: 0.98 | C8: ±2% | D8: stock-out revenue risk (63%) | E8: Autonomous | F8: ≤ $50K limit
A9: Raise PO FG-1003 (586u, $56,256) | B9: 0.88 | C9: ±12% | D9: stock-out revenue risk (86%) | E9: Human approval | F9: $56,256 > $50K limit
A12: Autonomy threshold = 85% confidence AND within the $50,000 value-based approval limit (human-in-the-loop above it).
A13: All 5 decisions ≥ 85% confidence; the held PO is gated on VALUE, not confidence — demonstrating policy-based governance.
